PyGreed/Greed.pyd
PyGreed/TransparentGrey.txt
PyGreed/__init__.py
PyGreed/client_v2_new.exe
PyGreed/example.pyd
PyGreed/main.py
PyGreed/mysqlcppconn-9-vs14.dll
PyGreed/mysqlcppconn8-2-vs14.dll
PyGreed/openal32.dll
PyGreed/position1.dat
PyGreed/position_sorted.dat
PyGreed/sfml-audio-2.dll
PyGreed/sfml-audio-d-2.dll
PyGreed/sfml-graphics-2.dll
PyGreed/sfml-graphics-d-2.dll
PyGreed/sfml-network-2.dll
PyGreed/sfml-network-d-2.dll
PyGreed/sfml-system-2.dll
PyGreed/sfml-system-d-2.dll
PyGreed/sfml-window-2.dll
PyGreed/sfml-window-d-2.dll
PyGreed/solo_by_river.wav
PyGreed/sqlite3.dll
PyGreed/tgui-d.dll
PyGreed/tgui.dll
PyGreed/user_algos.dll
PyGreed/Fonts/OpenSans-ExtraBoldItalic.ttf
PyGreed/Fonts/OpenSans-Italic.ttf
PyGreed/Fonts/OpenSans-LightItalic.ttf
PyGreed/Fonts/bold.ttf
PyGreed/Fonts/link.ttf
PyGreed/Fonts/number.ttf
PyGreed/Fonts/semiBoldItalic.ttf
PyGreed/Fonts/tabs.ttf
PyGreed/Fonts/text.ttf
PyGreed/Fonts/use.ttf
PyGreed/GUI attributes/Black.png
PyGreed/GUI attributes/Black.txt
PyGreed/GUI attributes/arrow.png
PyGreed/GUI attributes/arrow1.png
PyGreed/GUI attributes/wall.png
PyGreed/Matrix_images/frame_00_delay-0.png
PyGreed/Matrix_images/frame_01_delay-0.png
PyGreed/Matrix_images/frame_02_delay-0.png
PyGreed/Matrix_images/frame_03_delay-0.png
PyGreed/Matrix_images/frame_04_delay-0.png
PyGreed/Matrix_images/frame_05_delay-0.png
PyGreed/Matrix_images/frame_06_delay-0.png
PyGreed/Matrix_images/frame_07_delay-0.png
PyGreed/Matrix_images/frame_08_delay-0.png
PyGreed/Matrix_images/frame_09_delay-0.png
PyGreed/Matrix_images/frame_10_delay-0.png
PyGreed/Matrix_images/frame_11_delay-0.png
PyGreed/Matrix_images/frame_12_delay-0.png
PyGreed/Matrix_images/frame_13_delay-0.png
PyGreed/Matrix_images/frame_14_delay-0.png
PyGreed/Matrix_images/frame_15_delay-0.png
PyGreed/Matrix_images/frame_16_delay-0.png
PyGreed/Matrix_images/frame_17_delay-0.png
PyGreed/Matrix_images/frame_18_delay-0.png
PyGreed/Matrix_images/frame_19_delay-0.png
PyGreed/Matrix_images/frame_20_delay-0.png
PyGreed-0.31.dist-info/METADATA
PyGreed-0.31.dist-info/WHEEL
PyGreed-0.31.dist-info/entry_points.txt
PyGreed-0.31.dist-info/top_level.txt
PyGreed-0.31.dist-info/RECORD
