Metadata-Version: 2.1
Name: PyGreed
Version: 0.31
Summary: A package to start the Greed game with custom user algorithms
Home-page: https://github.com/PHANTOM9009/GREED
Author: ANCHIT RANA
Author-email: anchitrana4@gmail.com
Classifier: Programming Language :: Python :: 3
Classifier: License :: OSI Approved :: MIT License
Classifier: Operating System :: OS Independent
Requires-Python: >=3.6
Requires-Dist: pybind11
